[
  {
    "label": "Sorry",
    "text": "Sorry"
  },
  {
    "label" : "Cheese",
    "text": "Cheese"
  },
  {
    "label": "Thank",
    "text": "Thank you so much"
  },
  {
    "label": "Selfie",
    "text": "It is selfie time yall should take a selfie with me"
  },
  {
    "label": "Hey",
    "text": "Hey"
  },
  {
    "label": "Chill Bro",
    "text" : "Chill out brother"
  },
  {
    "label": "Freeze",
    "text" : "Freeze"
  },
  {
    "label": "Name",
    "text": "hello mah name is Anna bell ah am a robot with Bot Party, an interactive human and robot experience."
  },
  {
    "label" : "Chill sis",
    "text" : "Chill out sister"
  }
]